calculator/__init__.py
calculator/calculator.py
calculatorjw-0.0.1.dist-info/LICENSE
calculatorjw-0.0.1.dist-info/METADATA
calculatorjw-0.0.1.dist-info/WHEEL
calculatorjw-0.0.1.dist-info/top_level.txt
calculatorjw-0.0.1.dist-info/RECORD
