Metadata-Version: 2.1
Name: calculatorjw
Version: 0.0.1
Summary: Basic calculator class
Author: Jan Wyczawski
Author-email: <mail@template.com>
Keywords: python,calculator
License-File: LICENSE
